<PAMDataset>
  <Metadata>
    <MDI key="DataType">Generic</MDI>
  </Metadata>
  <Metadata domain="Esri">
    <MDI key="PyramidResamplingType">NEAREST</MDI>
  </Metadata>
  <PAMRasterBand band="1">
    <Histograms>
      <HistItem>
        <HistMin>0.8687765598297119</HistMin>
        <HistMax>77.96189880371094</HistMax>
        <BucketCount>256</BucketCount>
        <IncludeOutOfRange>1</IncludeOutOfRange>
        <Approximate>0</Approximate>
        <HistCounts>4|34|2449|15320|8937|15264|16561|19731|25149|20876|20656|21408|20224|21603|21309|21643|23374|25223|22540|22858|24192|24634|24383|23237|22924|22468|23298|24689|25876|25028|26154|23873|22543|22008|22000|21099|20592|19833|19429|18466|18456|18116|18506|18306|18454|18642|16910|16804|16983|17140|16569|16459|16019|16289|16578|16874|17401|17433|17461|17253|17278|17219|17591|18328|17648|17056|17258|17251|16980|16834|16713|17032|17085|17215|17263|16834|17141|17295|17366|17393|18375|17764|17203|16741|16311|16326|15914|16180|15798|15590|15605|15961|16021|16154|16518|16833|16680|17400|17555|17670|18201|18900|18539|19122|18478|18086|17509|17254|17696|17525|17758|17798|17235|16835|16703|16465|16160|15955|16121|16347|16527|16149|15896|15684|15554|15533|15522|15554|14845|14417|14287|14424|14433|14788|15106|15901|16224|16417|16941|19147|18485|17486|16983|16867|16990|16991|17354|18140|18318|18879|19258|19797|19540|18698|19035|18792|18801|18946|18486|18817|19856|22396|24870|25218|23433|22805|24562|26282|25859|25924|27402|28327|29658|30784|30038|31069|28714|29201|28315|30472|32147|34346|38049|41232|46610|43547|40257|39095|39759|37554|37363|38728|34187|35726|37608|35510|32555|31357|30823|30319|29182|28405|27755|29037|29166|31189|32451|34045|32968|33187|33368|33560|33180|35058|37951|39944|40373|42369|49528|53465|58112|51083|50665|51790|51862|46143|42612|44542|39963|41582|48286|43806|38082|29237|25962|26619|26637|27271|31558|24459|20135|16101|15168|18132|15950|9976|6102|5792|4889|3747|2500|1672|556|403|118|1</HistCounts>
      </HistItem>
    </Histograms>
    <Metadata>
      <MDI key="SourceBandIndex">0</MDI>
      <MDI key="STATISTICS_COVARIANCES">485.5496012435017</MDI>
      <MDI key="STATISTICS_EXCLUDEDVALUES"></MDI>
      <MDI key="STATISTICS_MAXIMUM">77.961898803711</MDI>
      <MDI key="STATISTICS_MEAN">43.724230704805</MDI>
      <MDI key="STATISTICS_MINIMUM">0.86877655982971</MDI>
      <MDI key="STATISTICS_SKIPFACTORX">1</MDI>
      <MDI key="STATISTICS_SKIPFACTORY">1</MDI>
      <MDI key="STATISTICS_STDDEV">22.035190065972</MDI>
    </Metadata>
  </PAMRasterBand>
</PAMDataset>
